tifresi/__init__.py
tifresi/hparams.py
tifresi/metrics.py
tifresi/stft.py
tifresi/transforms.py
tifresi/utils.py
tifresi/phase/__init__.py
tifresi/phase/modGabPhaseGrad.py
tifresi/phase/pghi.py
tifresi/phase/pghi_masked.py
tifresi/pipelines/LJparams.py
tifresi/pipelines/LJspeech.py
tifresi/pipelines/__init__.py
tifresi/tests/__init__.py
tifresi/tests/test_stft.py
tifresi/tests/test_transforms.py
tifresi-0.1.4.dist-info/LICENCE.txt
tifresi-0.1.4.dist-info/METADATA
tifresi-0.1.4.dist-info/WHEEL
tifresi-0.1.4.dist-info/top_level.txt
tifresi-0.1.4.dist-info/RECORD
