Metadata-Version: 2.1
Name: tifresi
Version: 0.1.4
Summary: Time Frequency Spectrogram Inversion
Home-page: https://github.com/andimarafioti/tifresi
Author: Andrés Marafioti, Nathanael Perraudin, Nicki Hollighaus
Author-email: nathanael.perraudin@sdsc.ethz.ch
License: MIT
Platform: UNKNOWN
Classifier: Development Status :: 5 - Production/Stable
Classifier: Intended Audience :: Science/Research
Classifier: Intended Audience :: End Users/Desktop
Classifier: Intended Audience :: Developers
Classifier: Natural Language :: English
Classifier: License :: OSI Approved :: GNU General Public License v3 (GPLv3)
Classifier: Operating System :: MacOS :: MacOS X
Classifier: Operating System :: POSIX :: Linux
Classifier: Programming Language :: C
Classifier: Programming Language :: Python :: 3.6
Classifier: Programming Language :: Python :: 3.7
Classifier: Programming Language :: Python :: 3.8
Classifier: Topic :: Scientific/Engineering :: Mathematics
Classifier: Topic :: Scientific/Engineering
Requires-Python: >=3.6
Requires-Dist: cython
Requires-Dist: ltfatpy
Requires-Dist: numpy
Requires-Dist: numba
Requires-Dist: librosa
Requires-Dist: matplotlib
Provides-Extra: testing
Requires-Dist: flake8 ; extra == 'testing'
Requires-Dist: pytest ; extra == 'testing'
Requires-Dist: jupyterlab ; extra == 'testing'
Requires-Dist: twine ; extra == 'testing'
Requires-Dist: setuptools ; extra == 'testing'
Requires-Dist: wheel ; extra == 'testing'
